boka_mpl_templates/__init__.py
boka_mpl_templates/__version__.py
boka_mpl_templates/footers.py
boka_mpl_templates/headers.py
boka_mpl_templates/resources/boskalis.png
boka_mpl_templates/schemas/__init__.py
boka_mpl_templates/schemas/plot.py
boka_mpl_templates/schemas/template.py
boka_mpl_templates/template.py
boka_mpl_templates/title_blocks.py
boka_mpl_templates/utils.py
boka_mpl_templates-0.2.0.dist-info/WHEEL
boka_mpl_templates-0.2.0.dist-info/METADATA
boka_mpl_templates-0.2.0.dist-info/RECORD
